shine2mqtt/__init__.py
shine2mqtt/__main__.py
shine2mqtt/app.py
shine2mqtt/cli.py
shine2mqtt/config.py
shine2mqtt/logger.py
shine2mqtt/api/__init__.py
shine2mqtt/api/api.py
shine2mqtt/api/config.py
shine2mqtt/growatt/__init__.py
shine2mqtt/growatt/client/__init__.py
shine2mqtt/growatt/client/config.py
shine2mqtt/growatt/client/generator.py
shine2mqtt/growatt/client/simulate.py
shine2mqtt/growatt/protocol/command.py
shine2mqtt/growatt/protocol/config.py
shine2mqtt/growatt/protocol/constants.py
shine2mqtt/growatt/protocol/decoders/__init__.py
shine2mqtt/growatt/protocol/decoders/ack.py
shine2mqtt/growatt/protocol/decoders/announce.py
shine2mqtt/growatt/protocol/decoders/base.py
shine2mqtt/growatt/protocol/decoders/config.py
shine2mqtt/growatt/protocol/decoders/data.py
shine2mqtt/growatt/protocol/decoders/header.py
shine2mqtt/growatt/protocol/decoders/ping.py
shine2mqtt/growatt/protocol/decoders/registry.py
shine2mqtt/growatt/protocol/encoders/__init__.py
shine2mqtt/growatt/protocol/encoders/ack.py
shine2mqtt/growatt/protocol/encoders/announce.py
shine2mqtt/growatt/protocol/encoders/base.py
shine2mqtt/growatt/protocol/encoders/config.py
shine2mqtt/growatt/protocol/encoders/crc.py
shine2mqtt/growatt/protocol/encoders/data.py
shine2mqtt/growatt/protocol/encoders/header.py
shine2mqtt/growatt/protocol/encoders/ping.py
shine2mqtt/growatt/protocol/encoders/registry.py
shine2mqtt/growatt/protocol/frame/__init__.py
shine2mqtt/growatt/protocol/frame/cipher.py
shine2mqtt/growatt/protocol/frame/crc.py
shine2mqtt/growatt/protocol/frame/decoder.py
shine2mqtt/growatt/protocol/frame/encoder.py
shine2mqtt/growatt/protocol/frame/factory.py
shine2mqtt/growatt/protocol/frame/validator.py
shine2mqtt/growatt/protocol/frame/capturer/__init__.py
shine2mqtt/growatt/protocol/frame/capturer/capturer.py
shine2mqtt/growatt/protocol/frame/capturer/handler.py
shine2mqtt/growatt/protocol/frame/capturer/sanitizer.py
shine2mqtt/growatt/protocol/messages/__init__.py
shine2mqtt-0.0.1.dist-info/METADATA
shine2mqtt-0.0.1.dist-info/WHEEL
shine2mqtt-0.0.1.dist-info/entry_points.txt
shine2mqtt-0.0.1.dist-info/licenses/LICENSE
shine2mqtt-0.0.1.dist-info/RECORD
