Metadata-Version: 2.4
Name: shine2mqtt
Version: 0.0.1
Summary: A local Growatt server which listens to your Shine Wifi-X datalogger and publishes to MQTT
Project-URL: Homepage, https://github.com/bremme/shine2mqtt
Project-URL: Issues, https://github.com/bremme/shine2mqtt/issues
Author-email: Bram Harmsen <crazed-lint-kisser@duck.com>
License-Expression: GPL-3.0
License-File: LICENSE
Classifier: Operating System :: OS Independent
Classifier: Programming Language :: Python :: 3
Requires-Python: >=3.14
Requires-Dist: aiomqtt>=2.5.0
Requires-Dist: fastapi>=0.128.0
Requires-Dist: loguru>=0.7.3
Requires-Dist: pydantic-settings>=2.0.0
Requires-Dist: pydantic>=2.12.5
Requires-Dist: pyyaml>=6.0.3
Requires-Dist: uvicorn>=0.40.0
